COPYRIGHT.txt
LICENSE.txt
MANIFEST.in
README.txt
setup.cfg
setup.py
tox.ini
version.py
docs/HISTORY.txt
docs/Makefile
docs/api.txt
docs/conf.py
docs/index.txt
gs/__init__.py
gs.core.egg-info/PKG-INFO
gs.core.egg-info/SOURCES.txt
gs.core.egg-info/dependency_links.txt
gs.core.egg-info/entry_points.txt
gs.core.egg-info/namespace_packages.txt
gs.core.egg-info/not-zip-safe
gs.core.egg-info/requires.txt
gs.core.egg-info/top_level.txt
gs/core/__init__.py
gs/core/identifiers.py
gs/core/utils.py
gs/core/test/__init__.py
gs/core/test/identifiers.py
gs/core/test/test_all.py
gs/core/test/utils.py