Metadata-Version: 1.1
Name: gs.core
Version: 2.1.1
Summary: Useful utility functions.
Home-page: https://source.iopen.net/groupserver/gs.core/
Author: Michael JasonSmith
Author-email: mpj17@onlinegroups.net
License: ZPL 2.1
Keywords: zope form formlib zope.formlib post
Platform: UNKNOWN
Classifier: Development Status :: 5 - Production/Stable
Classifier: Intended Audience :: Developers
Classifier: License :: OSI Approved :: Zope Public License
Classifier: Natural Language :: English
Classifier: Operating System :: OS Independent
Classifier: Programming Language :: Python
Classifier: Programming Language :: Python :: 2
Classifier: Programming Language :: Python :: 2.7
Classifier: Programming Language :: Python :: 3
Classifier: Programming Language :: Python :: 3.3
Classifier: Programming Language :: Python :: 3.4
Classifier: Programming Language :: Python :: Implementation :: CPython
Classifier: Programming Language :: Python :: Implementation :: PyPy
Classifier: Topic :: Software Development :: Libraries :: Python Modules
